exsim/__init__.py
exsim/api.py
exsim/book.py
exsim/endpoint.py
exsim/engine.py
exsim/fix.py
exsim/fix_parser.py
exsim/fix_protocol.py
exsim/manager.py
exsim/market.py
exsim/message.py
exsim/order.py
exsim/protocol.py
exsim/server.py
exsim/session.py
exsim/side.py
exsim/version.py
python_exsim-0.0.2.dist-info/LICENSE
python_exsim-0.0.2.dist-info/METADATA
python_exsim-0.0.2.dist-info/WHEEL
python_exsim-0.0.2.dist-info/top_level.txt
python_exsim-0.0.2.dist-info/RECORD
